vivqu/.DS_Store
vivqu/__init__.py
vivqu/loader.py
vivqu/quality_check/__init__.py
vivqu/quality_check/checker.py
vivqu/quality_check/deequ_wrap.py
vivqu/quality_check/verification.py
vivqu/quality_check/viv_type.py
vivqu/visualize/__init__.py
vivqu/visualize/plot.py
vivqu/visualize/subfig.py
vivqu-0.0.6.dist-info/METADATA
vivqu-0.0.6.dist-info/WHEEL
vivqu-0.0.6.dist-info/licenses/LICENSE
vivqu-0.0.6.dist-info/RECORD
