Metadata-Version: 2.1
Name: vivqu
Version: 0.0.6
Summary: Easier data analysis and visualization based on pydeequ
Project-URL: Repository, https://gitlab.awx.im/awx-platform/ml-platform/risk-data-quality-check/
Author-email: Ding Yang <yangding19thu@outlook.com>
Classifier: Development Status :: 3 - Alpha
Classifier: License :: OSI Approved :: Apache Software License
Classifier: Operating System :: OS Independent
Classifier: Programming Language :: Python :: 3
Requires-Python: >=3.7
Requires-Dist: heatmapz
Requires-Dist: pydeequ
Requires-Dist: pyspark
